[
  {
    "location_id": 193,
    "votes": 1,
    "proportion": 0.01,
    "total_votes_location": 7412
  },
  {
    "location_id": 245,
    "votes": 1,
    "proportion": 0.02,
    "total_votes_location": 6101
  },
  {
    "location_id": 749,
    "votes": 2,
    "proportion": 0.06,
    "total_votes_location": 3348
  },
  {
    "location_id": 597,
    "votes": 1,
    "proportion": 0.04,
    "total_votes_location": 2442
  },
  {
    "location_id": 497,
    "votes": 1,
    "proportion": 0.04,
    "total_votes_location": 2552
  },
  {
    "location_id": 564,
    "votes": 1,
    "proportion": 0.02,
    "total_votes_location": 5319
  },
  {
    "location_id": 679,
    "votes": 2,
    "proportion": 0.06,
    "total_votes_location": 3635
  },
  {
    "location_id": 107,
    "votes": 1,
    "proportion": 0.02,
    "total_votes_location": 4181
  },
  {
    "location_id": 499,
    "votes": 1,
    "proportion": 0.03,
    "total_votes_location": 3109
  },
  {
    "location_id": 1121,
    "votes": 3,
    "proportion": 0.07,
    "total_votes_location": 4408
  },
  {
    "location_id": 504,
    "votes": 1,
    "proportion": 0.02,
    "total_votes_location": 4881
  },
  {
    "location_id": 539,
    "votes": 1,
    "proportion": 0.03,
    "total_votes_location": 3148
  },
  {
    "location_id": 645,
    "votes": 1,
    "proportion": 0.02,
    "total_votes_location": 4878
  },
  {
    "location_id": 1246,
    "votes": 1,
    "proportion": 0.01,
    "total_votes_location": 7388
  },
  {
    "location_id": 395,
    "votes": 1,
    "proportion": 0.01,
    "total_votes_location": 8581
  },
  {
    "location_id": 352,
    "votes": 1,
    "proportion": 0.04,
    "total_votes_location": 2443
  },
  {
    "location_id": 532,
    "votes": 3,
    "proportion": 0.05,
    "total_votes_location": 5916
  },
  {
    "location_id": 1334,
    "votes": 2,
    "proportion": 0.05,
    "total_votes_location": 3834
  },
  {
    "location_id": 1268,
    "votes": 1,
    "proportion": 0.01,
    "total_votes_location": 10047
  },
  {
    "location_id": 1050,
    "votes": 1,
    "proportion": 0.01,
    "total_votes_location": 6904
  },
  {
    "location_id": 1374,
    "votes": 1,
    "proportion": 0.03,
    "total_votes_location": 2946
  },
  {
    "location_id": 897,
    "votes": 5,
    "proportion": 0.08,
    "total_votes_location": 6271
  },
  {
    "location_id": 153,
    "votes": 1,
    "proportion": 0.03,
    "total_votes_location": 3676
  },
  {
    "location_id": 1176,
    "votes": 1,
    "proportion": 0.02,
    "total_votes_location": 4564
  },
  {
    "location_id": 834,
    "votes": 1,
    "proportion": 0.01,
    "total_votes_location": 6687
  },
  {
    "location_id": 1090,
    "votes": 2,
    "proportion": 0.05,
    "total_votes_location": 3769
  },
  {
    "location_id": 1173,
    "votes": 1,
    "proportion": 0.02,
    "total_votes_location": 4996
  },
  {
    "location_id": 130,
    "votes": 1,
    "proportion": 0.05,
    "total_votes_location": 2219
  },
  {
    "location_id": 1388,
    "votes": 1,
    "proportion": 0.01,
    "total_votes_location": 8398
  },
  {
    "location_id": 909,
    "votes": 1,
    "proportion": 0.02,
    "total_votes_location": 6112
  },
  {
    "location_id": 547,
    "votes": 1,
    "proportion": 0.02,
    "total_votes_location": 6365
  },
  {
    "location_id": 1184,
    "votes": 1,
    "proportion": 0.02,
    "total_votes_location": 4665
  },
  {
    "location_id": 1125,
    "votes": 2,
    "proportion": 0.03,
    "total_votes_location": 6247
  },
  {
    "location_id": 1017,
    "votes": 1,
    "proportion": 0.06,
    "total_votes_location": 1635
  },
  {
    "location_id": 774,
    "votes": 1,
    "proportion": 0.03,
    "total_votes_location": 3576
  },
  {
    "location_id": 664,
    "votes": 1,
    "proportion": 0.02,
    "total_votes_location": 4039
  },
  {
    "location_id": 873,
    "votes": 3,
    "proportion": 0.1,
    "total_votes_location": 3011
  },
  {
    "location_id": 933,
    "votes": 1,
    "proportion": 0.02,
    "total_votes_location": 6022
  },
  {
    "location_id": 752,
    "votes": 1,
    "proportion": 0.02,
    "total_votes_location": 4888
  },
  {
    "location_id": 643,
    "votes": 1,
    "proportion": 0.03,
    "total_votes_location": 3905
  },
  {
    "location_id": 1209,
    "votes": 1,
    "proportion": 0.02,
    "total_votes_location": 4517
  },
  {
    "location_id": 487,
    "votes": 1,
    "proportion": 0.01,
    "total_votes_location": 7389
  },
  {
    "location_id": 1211,
    "votes": 1,
    "proportion": 0.04,
    "total_votes_location": 2411
  },
  {
    "location_id": 596,
    "votes": 1,
    "proportion": 0.02,
    "total_votes_location": 4828
  },
  {
    "location_id": 386,
    "votes": 1,
    "proportion": 0.03,
    "total_votes_location": 3716
  },
  {
    "location_id": 238,
    "votes": 1,
    "proportion": 0.01,
    "total_votes_location": 11023
  },
  {
    "location_id": 1089,
    "votes": 2,
    "proportion": 0.05,
    "total_votes_location": 3776
  },
  {
    "location_id": 290,
    "votes": 2,
    "proportion": 0.04,
    "total_votes_location": 4555
  },
  {
    "location_id": 433,
    "votes": 1,
    "proportion": 0.04,
    "total_votes_location": 2276
  },
  {
    "location_id": 286,
    "votes": 1,
    "proportion": 0.01,
    "total_votes_location": 11655
  },
  {
    "location_id": 205,
    "votes": 2,
    "proportion": 0.02,
    "total_votes_location": 8165
  },
  {
    "location_id": 841,
    "votes": 1,
    "proportion": 0.03,
    "total_votes_location": 3567
  },
  {
    "location_id": 559,
    "votes": 1,
    "proportion": 0.01,
    "total_votes_location": 8203
  },
  {
    "location_id": 593,
    "votes": 1,
    "proportion": 0.01,
    "total_votes_location": 7204
  },
  {
    "location_id": 417,
    "votes": 1,
    "proportion": 0.01,
    "total_votes_location": 10462
  },
  {
    "location_id": 674,
    "votes": 1,
    "proportion": 0.02,
    "total_votes_location": 5591
  },
  {
    "location_id": 549,
    "votes": 1,
    "proportion": 0.03,
    "total_votes_location": 3180
  },
  {
    "location_id": 162,
    "votes": 1,
    "proportion": 0.02,
    "total_votes_location": 5600
  },
  {
    "location_id": 181,
    "votes": 1,
    "proportion": 0.02,
    "total_votes_location": 6194
  },
  {
    "location_id": 1073,
    "votes": 1,
    "proportion": 0.01,
    "total_votes_location": 7085
  },
  {
    "location_id": 232,
    "votes": 1,
    "proportion": 0.01,
    "total_votes_location": 8855
  },
  {
    "location_id": 629,
    "votes": 1,
    "proportion": 0.01,
    "total_votes_location": 7579
  },
  {
    "location_id": 523,
    "votes": 1,
    "proportion": 0.03,
    "total_votes_location": 3387
  },
  {
    "location_id": 1043,
    "votes": 1,
    "proportion": 0.01,
    "total_votes_location": 7640
  },
  {
    "location_id": 1164,
    "votes": 1,
    "proportion": 0.03,
    "total_votes_location": 3848
  },
  {
    "location_id": 849,
    "votes": 2,
    "proportion": 0.03,
    "total_votes_location": 6361
  },
  {
    "location_id": 1080,
    "votes": 1,
    "proportion": 0.01,
    "total_votes_location": 7059
  },
  {
    "location_id": 716,
    "votes": 2,
    "proportion": 0.15,
    "total_votes_location": 1304
  },
  {
    "location_id": 830,
    "votes": 3,
    "proportion": 0.07,
    "total_votes_location": 4442
  },
  {
    "location_id": 128,
    "votes": 1,
    "proportion": 0.02,
    "total_votes_location": 4794
  },
  {
    "location_id": 760,
    "votes": 1,
    "proportion": 0.03,
    "total_votes_location": 3318
  }
]