[
  {
    "location_id": 1229,
    "votes": 1,
    "proportion": 0.04,
    "total_votes_location": 2227
  },
  {
    "location_id": 900,
    "votes": 1,
    "proportion": 0.01,
    "total_votes_location": 6745
  },
  {
    "location_id": 483,
    "votes": 2,
    "proportion": 0.04,
    "total_votes_location": 5104
  },
  {
    "location_id": 899,
    "votes": 1,
    "proportion": 0.03,
    "total_votes_location": 3821
  },
  {
    "location_id": 682,
    "votes": 1,
    "proportion": 0.02,
    "total_votes_location": 4185
  },
  {
    "location_id": 1277,
    "votes": 1,
    "proportion": 0.04,
    "total_votes_location": 2270
  },
  {
    "location_id": 60,
    "votes": 1,
    "proportion": 0.1,
    "total_votes_location": 992
  },
  {
    "location_id": 1165,
    "votes": 1,
    "proportion": 0.01,
    "total_votes_location": 6791
  },
  {
    "location_id": 1265,
    "votes": 1,
    "proportion": 0.04,
    "total_votes_location": 2468
  },
  {
    "location_id": 1035,
    "votes": 1,
    "proportion": 0.02,
    "total_votes_location": 5626
  },
  {
    "location_id": 652,
    "votes": 5,
    "proportion": 0.12,
    "total_votes_location": 4066
  },
  {
    "location_id": 347,
    "votes": 2,
    "proportion": 0.04,
    "total_votes_location": 5151
  },
  {
    "location_id": 869,
    "votes": 1,
    "proportion": 0.02,
    "total_votes_location": 4851
  },
  {
    "location_id": 1207,
    "votes": 1,
    "proportion": 0.03,
    "total_votes_location": 2951
  },
  {
    "location_id": 302,
    "votes": 2,
    "proportion": 0.05,
    "total_votes_location": 4373
  },
  {
    "location_id": 651,
    "votes": 1,
    "proportion": 0.04,
    "total_votes_location": 2583
  },
  {
    "location_id": 810,
    "votes": 1,
    "proportion": 0.04,
    "total_votes_location": 2489
  },
  {
    "location_id": 444,
    "votes": 1,
    "proportion": 0.01,
    "total_votes_location": 9551
  },
  {
    "location_id": 193,
    "votes": 2,
    "proportion": 0.03,
    "total_votes_location": 7412
  },
  {
    "location_id": 890,
    "votes": 1,
    "proportion": 0.02,
    "total_votes_location": 5138
  },
  {
    "location_id": 1213,
    "votes": 6,
    "proportion": 0.08,
    "total_votes_location": 7124
  },
  {
    "location_id": 1413,
    "votes": 1,
    "proportion": 0.01,
    "total_votes_location": 13835
  },
  {
    "location_id": 678,
    "votes": 1,
    "proportion": 0.04,
    "total_votes_location": 2847
  },
  {
    "location_id": 417,
    "votes": 1,
    "proportion": 0.01,
    "total_votes_location": 10462
  },
  {
    "location_id": 566,
    "votes": 1,
    "proportion": 0.03,
    "total_votes_location": 3325
  },
  {
    "location_id": 133,
    "votes": 1,
    "proportion": 0.02,
    "total_votes_location": 6115
  },
  {
    "location_id": 945,
    "votes": 2,
    "proportion": 0.09,
    "total_votes_location": 2115
  },
  {
    "location_id": 868,
    "votes": 1,
    "proportion": 0.05,
    "total_votes_location": 1938
  },
  {
    "location_id": 1083,
    "votes": 1,
    "proportion": 0.02,
    "total_votes_location": 5329
  },
  {
    "location_id": 910,
    "votes": 2,
    "proportion": 0.08,
    "total_votes_location": 2513
  },
  {
    "location_id": 1096,
    "votes": 1,
    "proportion": 0.01,
    "total_votes_location": 8684
  },
  {
    "location_id": 581,
    "votes": 1,
    "proportion": 0.04,
    "total_votes_location": 2523
  },
  {
    "location_id": 428,
    "votes": 1,
    "proportion": 0.07,
    "total_votes_location": 1451
  },
  {
    "location_id": 141,
    "votes": 1,
    "proportion": 0.04,
    "total_votes_location": 2763
  },
  {
    "location_id": 561,
    "votes": 1,
    "proportion": 0.02,
    "total_votes_location": 5294
  },
  {
    "location_id": 398,
    "votes": 1,
    "proportion": 0.01,
    "total_votes_location": 8049
  },
  {
    "location_id": 1175,
    "votes": 2,
    "proportion": 0.06,
    "total_votes_location": 3415
  },
  {
    "location_id": 117,
    "votes": 1,
    "proportion": 0.03,
    "total_votes_location": 2875
  },
  {
    "location_id": 363,
    "votes": 1,
    "proportion": 0.02,
    "total_votes_location": 5883
  },
  {
    "location_id": 949,
    "votes": 1,
    "proportion": 0.03,
    "total_votes_location": 3108
  },
  {
    "location_id": 368,
    "votes": 1,
    "proportion": 0.02,
    "total_votes_location": 4328
  },
  {
    "location_id": 234,
    "votes": 1,
    "proportion": 0.02,
    "total_votes_location": 4626
  },
  {
    "location_id": 460,
    "votes": 1,
    "proportion": 0.02,
    "total_votes_location": 4507
  },
  {
    "location_id": 445,
    "votes": 1,
    "proportion": 0.03,
    "total_votes_location": 3670
  },
  {
    "location_id": 815,
    "votes": 5,
    "proportion": 0.07,
    "total_votes_location": 7092
  },
  {
    "location_id": 824,
    "votes": 2,
    "proportion": 0.02,
    "total_votes_location": 10685
  },
  {
    "location_id": 129,
    "votes": 1,
    "proportion": 0.04,
    "total_votes_location": 2819
  },
  {
    "location_id": 896,
    "votes": 1,
    "proportion": 0.02,
    "total_votes_location": 5943
  },
  {
    "location_id": 296,
    "votes": 1,
    "proportion": 0.01,
    "total_votes_location": 7014
  },
  {
    "location_id": 333,
    "votes": 1,
    "proportion": 0.04,
    "total_votes_location": 2598
  },
  {
    "location_id": 689,
    "votes": 1,
    "proportion": 0.01,
    "total_votes_location": 6814
  },
  {
    "location_id": 766,
    "votes": 1,
    "proportion": 0.02,
    "total_votes_location": 4795
  },
  {
    "location_id": 149,
    "votes": 1,
    "proportion": 0.02,
    "total_votes_location": 4824
  },
  {
    "location_id": 1379,
    "votes": 1,
    "proportion": 0.01,
    "total_votes_location": 6900
  },
  {
    "location_id": 255,
    "votes": 1,
    "proportion": 0.03,
    "total_votes_location": 3503
  },
  {
    "location_id": 1139,
    "votes": 1,
    "proportion": 0.03,
    "total_votes_location": 2911
  },
  {
    "location_id": 592,
    "votes": 1,
    "proportion": 0.02,
    "total_votes_location": 5407
  },
  {
    "location_id": 892,
    "votes": 1,
    "proportion": 0.02,
    "total_votes_location": 6350
  },
  {
    "location_id": 89,
    "votes": 1,
    "proportion": 0.02,
    "total_votes_location": 5990
  },
  {
    "location_id": 1274,
    "votes": 1,
    "proportion": 0.04,
    "total_votes_location": 2570
  },
  {
    "location_id": 1193,
    "votes": 5,
    "proportion": 0.07,
    "total_votes_location": 7674
  },
  {
    "location_id": 395,
    "votes": 1,
    "proportion": 0.01,
    "total_votes_location": 8581
  },
  {
    "location_id": 1194,
    "votes": 1,
    "proportion": 0.03,
    "total_votes_location": 2861
  },
  {
    "location_id": 1024,
    "votes": 1,
    "proportion": 0.02,
    "total_votes_location": 4910
  },
  {
    "location_id": 806,
    "votes": 1,
    "proportion": 0.04,
    "total_votes_location": 2814
  },
  {
    "location_id": 802,
    "votes": 1,
    "proportion": 0.03,
    "total_votes_location": 3039
  },
  {
    "location_id": 127,
    "votes": 1,
    "proportion": 0.02,
    "total_votes_location": 4393
  },
  {
    "location_id": 1049,
    "votes": 1,
    "proportion": 0.02,
    "total_votes_location": 5241
  },
  {
    "location_id": 108,
    "votes": 1,
    "proportion": 0.04,
    "total_votes_location": 2393
  },
  {
    "location_id": 1392,
    "votes": 1,
    "proportion": 0.01,
    "total_votes_location": 13523
  },
  {
    "location_id": 717,
    "votes": 1,
    "proportion": 0.02,
    "total_votes_location": 4101
  },
  {
    "location_id": 311,
    "votes": 1,
    "proportion": 0.04,
    "total_votes_location": 2490
  },
  {
    "location_id": 1115,
    "votes": 1,
    "proportion": 0.01,
    "total_votes_location": 7063
  },
  {
    "location_id": 1023,
    "votes": 1,
    "proportion": 0.04,
    "total_votes_location": 2674
  },
  {
    "location_id": 233,
    "votes": 1,
    "proportion": 0.01,
    "total_votes_location": 8944
  },
  {
    "location_id": 863,
    "votes": 1,
    "proportion": 0.03,
    "total_votes_location": 3817
  },
  {
    "location_id": 139,
    "votes": 1,
    "proportion": 0.01,
    "total_votes_location": 7415
  },
  {
    "location_id": 1166,
    "votes": 1,
    "proportion": 0.04,
    "total_votes_location": 2750
  },
  {
    "location_id": 493,
    "votes": 1,
    "proportion": 0.02,
    "total_votes_location": 4976
  },
  {
    "location_id": 1001,
    "votes": 1,
    "proportion": 0.01,
    "total_votes_location": 6767
  },
  {
    "location_id": 1378,
    "votes": 1,
    "proportion": 0.04,
    "total_votes_location": 2610
  },
  {
    "location_id": 971,
    "votes": 4,
    "proportion": 0.07,
    "total_votes_location": 5674
  },
  {
    "location_id": 1263,
    "votes": 1,
    "proportion": 0.01,
    "total_votes_location": 9330
  },
  {
    "location_id": 883,
    "votes": 2,
    "proportion": 0.07,
    "total_votes_location": 2728
  },
  {
    "location_id": 17,
    "votes": 1,
    "proportion": 0.1,
    "total_votes_location": 1041
  },
  {
    "location_id": 239,
    "votes": 1,
    "proportion": 0.02,
    "total_votes_location": 4346
  },
  {
    "location_id": 1420,
    "votes": 1,
    "proportion": 0.01,
    "total_votes_location": 10532
  },
  {
    "location_id": 286,
    "votes": 1,
    "proportion": 0.01,
    "total_votes_location": 11655
  },
  {
    "location_id": 823,
    "votes": 1,
    "proportion": 0.03,
    "total_votes_location": 3020
  },
  {
    "location_id": 249,
    "votes": 1,
    "proportion": 0.04,
    "total_votes_location": 2634
  },
  {
    "location_id": 726,
    "votes": 1,
    "proportion": 0.02,
    "total_votes_location": 5515
  },
  {
    "location_id": 481,
    "votes": 1,
    "proportion": 0.03,
    "total_votes_location": 3813
  },
  {
    "location_id": 701,
    "votes": 2,
    "proportion": 0.06,
    "total_votes_location": 3536
  },
  {
    "location_id": 188,
    "votes": 1,
    "proportion": 0.03,
    "total_votes_location": 3247
  },
  {
    "location_id": 903,
    "votes": 1,
    "proportion": 0.04,
    "total_votes_location": 2287
  },
  {
    "location_id": 547,
    "votes": 1,
    "proportion": 0.02,
    "total_votes_location": 6365
  },
  {
    "location_id": 1264,
    "votes": 1,
    "proportion": 0.06,
    "total_votes_location": 1719
  },
  {
    "location_id": 156,
    "votes": 2,
    "proportion": 0.02,
    "total_votes_location": 8651
  },
  {
    "location_id": 1300,
    "votes": 1,
    "proportion": 0.06,
    "total_votes_location": 1726
  },
  {
    "location_id": 158,
    "votes": 1,
    "proportion": 0.02,
    "total_votes_location": 6584
  },
  {
    "location_id": 1187,
    "votes": 1,
    "proportion": 0.02,
    "total_votes_location": 6349
  },
  {
    "location_id": 1372,
    "votes": 1,
    "proportion": 0.04,
    "total_votes_location": 2545
  },
  {
    "location_id": 413,
    "votes": 1,
    "proportion": 0.01,
    "total_votes_location": 6793
  },
  {
    "location_id": 270,
    "votes": 1,
    "proportion": 0.01,
    "total_votes_location": 10426
  },
  {
    "location_id": 1191,
    "votes": 1,
    "proportion": 0.02,
    "total_votes_location": 4441
  },
  {
    "location_id": 1334,
    "votes": 1,
    "proportion": 0.03,
    "total_votes_location": 3834
  },
  {
    "location_id": 795,
    "votes": 1,
    "proportion": 0.03,
    "total_votes_location": 3755
  },
  {
    "location_id": 856,
    "votes": 1,
    "proportion": 0.01,
    "total_votes_location": 9832
  },
  {
    "location_id": 742,
    "votes": 1,
    "proportion": 0.02,
    "total_votes_location": 6332
  },
  {
    "location_id": 946,
    "votes": 1,
    "proportion": 0.03,
    "total_votes_location": 3432
  },
  {
    "location_id": 1275,
    "votes": 1,
    "proportion": 0.1,
    "total_votes_location": 956
  },
  {
    "location_id": 1171,
    "votes": 1,
    "proportion": 0.02,
    "total_votes_location": 5954
  },
  {
    "location_id": 425,
    "votes": 1,
    "proportion": 0.02,
    "total_votes_location": 5967
  },
  {
    "location_id": 90,
    "votes": 1,
    "proportion": 0.03,
    "total_votes_location": 3281
  },
  {
    "location_id": 933,
    "votes": 1,
    "proportion": 0.02,
    "total_votes_location": 6022
  },
  {
    "location_id": 794,
    "votes": 1,
    "proportion": 0.01,
    "total_votes_location": 7127
  },
  {
    "location_id": 994,
    "votes": 1,
    "proportion": 0.01,
    "total_votes_location": 7176
  }
]