[
  {
    "location_id": 1387,
    "votes": 2,
    "proportion": 0.06,
    "total_votes_location": 3136
  },
  {
    "location_id": 993,
    "votes": 1,
    "proportion": 0.02,
    "total_votes_location": 4606
  },
  {
    "location_id": 1282,
    "votes": 1,
    "proportion": 0.03,
    "total_votes_location": 2884
  },
  {
    "location_id": 1210,
    "votes": 1,
    "proportion": 0.05,
    "total_votes_location": 1864
  },
  {
    "location_id": 486,
    "votes": 1,
    "proportion": 0.03,
    "total_votes_location": 2941
  },
  {
    "location_id": 849,
    "votes": 1,
    "proportion": 0.02,
    "total_votes_location": 6361
  },
  {
    "location_id": 1372,
    "votes": 1,
    "proportion": 0.04,
    "total_votes_location": 2545
  },
  {
    "location_id": 76,
    "votes": 2,
    "proportion": 0.02,
    "total_votes_location": 8740
  },
  {
    "location_id": 1004,
    "votes": 1,
    "proportion": 0.02,
    "total_votes_location": 6561
  },
  {
    "location_id": 1073,
    "votes": 5,
    "proportion": 0.07,
    "total_votes_location": 7085
  },
  {
    "location_id": 159,
    "votes": 1,
    "proportion": 0.01,
    "total_votes_location": 8212
  },
  {
    "location_id": 278,
    "votes": 1,
    "proportion": 0.02,
    "total_votes_location": 6398
  },
  {
    "location_id": 1395,
    "votes": 1,
    "proportion": 0.02,
    "total_votes_location": 6434
  },
  {
    "location_id": 1172,
    "votes": 1,
    "proportion": 0.03,
    "total_votes_location": 3111
  },
  {
    "location_id": 1394,
    "votes": 1,
    "proportion": 0.02,
    "total_votes_location": 6538
  },
  {
    "location_id": 1360,
    "votes": 1,
    "proportion": 0.03,
    "total_votes_location": 2986
  },
  {
    "location_id": 1419,
    "votes": 1,
    "proportion": 0.01,
    "total_votes_location": 7187
  },
  {
    "location_id": 1318,
    "votes": 1,
    "proportion": 0.05,
    "total_votes_location": 2141
  },
  {
    "location_id": 843,
    "votes": 3,
    "proportion": 0.04,
    "total_votes_location": 7572
  },
  {
    "location_id": 1385,
    "votes": 1,
    "proportion": 0.01,
    "total_votes_location": 7521
  },
  {
    "location_id": 1218,
    "votes": 1,
    "proportion": 0.04,
    "total_votes_location": 2704
  },
  {
    "location_id": 253,
    "votes": 1,
    "proportion": 0.02,
    "total_votes_location": 5211
  },
  {
    "location_id": 1341,
    "votes": 1,
    "proportion": 0.04,
    "total_votes_location": 2615
  },
  {
    "location_id": 1019,
    "votes": 1,
    "proportion": 0.02,
    "total_votes_location": 4527
  },
  {
    "location_id": 771,
    "votes": 1,
    "proportion": 0.04,
    "total_votes_location": 2622
  },
  {
    "location_id": 980,
    "votes": 1,
    "proportion": 0.03,
    "total_votes_location": 3658
  },
  {
    "location_id": 54,
    "votes": 1,
    "proportion": 0.04,
    "total_votes_location": 2379
  },
  {
    "location_id": 621,
    "votes": 1,
    "proportion": 0.02,
    "total_votes_location": 6590
  },
  {
    "location_id": 919,
    "votes": 2,
    "proportion": 0.03,
    "total_votes_location": 6898
  },
  {
    "location_id": 700,
    "votes": 3,
    "proportion": 0.04,
    "total_votes_location": 8008
  },
  {
    "location_id": 1346,
    "votes": 1,
    "proportion": 0.02,
    "total_votes_location": 4147
  },
  {
    "location_id": 287,
    "votes": 1,
    "proportion": 0.02,
    "total_votes_location": 5391
  },
  {
    "location_id": 604,
    "votes": 1,
    "proportion": 0.02,
    "total_votes_location": 4539
  },
  {
    "location_id": 925,
    "votes": 2,
    "proportion": 0.04,
    "total_votes_location": 4779
  },
  {
    "location_id": 903,
    "votes": 1,
    "proportion": 0.04,
    "total_votes_location": 2287
  },
  {
    "location_id": 1358,
    "votes": 2,
    "proportion": 0.08,
    "total_votes_location": 2588
  },
  {
    "location_id": 1222,
    "votes": 1,
    "proportion": 0.04,
    "total_votes_location": 2796
  },
  {
    "location_id": 545,
    "votes": 1,
    "proportion": 0.02,
    "total_votes_location": 5411
  },
  {
    "location_id": 978,
    "votes": 1,
    "proportion": 0.02,
    "total_votes_location": 6454
  },
  {
    "location_id": 900,
    "votes": 1,
    "proportion": 0.01,
    "total_votes_location": 6745
  },
  {
    "location_id": 1392,
    "votes": 1,
    "proportion": 0.01,
    "total_votes_location": 13523
  },
  {
    "location_id": 363,
    "votes": 1,
    "proportion": 0.02,
    "total_votes_location": 5883
  },
  {
    "location_id": 202,
    "votes": 2,
    "proportion": 0.03,
    "total_votes_location": 6143
  },
  {
    "location_id": 1005,
    "votes": 2,
    "proportion": 0.03,
    "total_votes_location": 6463
  },
  {
    "location_id": 838,
    "votes": 2,
    "proportion": 0.04,
    "total_votes_location": 5067
  },
  {
    "location_id": 953,
    "votes": 1,
    "proportion": 0.03,
    "total_votes_location": 3651
  },
  {
    "location_id": 695,
    "votes": 1,
    "proportion": 0.01,
    "total_votes_location": 13031
  },
  {
    "location_id": 331,
    "votes": 1,
    "proportion": 0.03,
    "total_votes_location": 2953
  },
  {
    "location_id": 384,
    "votes": 1,
    "proportion": 0.01,
    "total_votes_location": 7774
  },
  {
    "location_id": 1339,
    "votes": 1,
    "proportion": 0.02,
    "total_votes_location": 5138
  },
  {
    "location_id": 68,
    "votes": 1,
    "proportion": 0.03,
    "total_votes_location": 3372
  },
  {
    "location_id": 289,
    "votes": 1,
    "proportion": 0.02,
    "total_votes_location": 4539
  },
  {
    "location_id": 1104,
    "votes": 1,
    "proportion": 0.02,
    "total_votes_location": 6132
  },
  {
    "location_id": 1265,
    "votes": 1,
    "proportion": 0.04,
    "total_votes_location": 2468
  },
  {
    "location_id": 405,
    "votes": 1,
    "proportion": 0.04,
    "total_votes_location": 2533
  },
  {
    "location_id": 750,
    "votes": 1,
    "proportion": 0.03,
    "total_votes_location": 2858
  },
  {
    "location_id": 267,
    "votes": 2,
    "proportion": 0.05,
    "total_votes_location": 4148
  },
  {
    "location_id": 1117,
    "votes": 1,
    "proportion": 0.03,
    "total_votes_location": 2882
  },
  {
    "location_id": 1300,
    "votes": 1,
    "proportion": 0.06,
    "total_votes_location": 1726
  },
  {
    "location_id": 376,
    "votes": 1,
    "proportion": 0.02,
    "total_votes_location": 4451
  },
  {
    "location_id": 595,
    "votes": 1,
    "proportion": 0.02,
    "total_votes_location": 5138
  },
  {
    "location_id": 1239,
    "votes": 1,
    "proportion": 0.03,
    "total_votes_location": 3974
  },
  {
    "location_id": 1064,
    "votes": 1,
    "proportion": 0.05,
    "total_votes_location": 2178
  },
  {
    "location_id": 1342,
    "votes": 1,
    "proportion": 0.02,
    "total_votes_location": 6154
  },
  {
    "location_id": 997,
    "votes": 2,
    "proportion": 0.05,
    "total_votes_location": 3681
  },
  {
    "location_id": 892,
    "votes": 1,
    "proportion": 0.02,
    "total_votes_location": 6350
  },
  {
    "location_id": 819,
    "votes": 2,
    "proportion": 0.03,
    "total_votes_location": 6507
  },
  {
    "location_id": 419,
    "votes": 1,
    "proportion": 0.01,
    "total_votes_location": 6809
  },
  {
    "location_id": 45,
    "votes": 1,
    "proportion": 0.04,
    "total_votes_location": 2414
  },
  {
    "location_id": 238,
    "votes": 2,
    "proportion": 0.02,
    "total_votes_location": 11023
  },
  {
    "location_id": 351,
    "votes": 1,
    "proportion": 0.04,
    "total_votes_location": 2333
  },
  {
    "location_id": 778,
    "votes": 1,
    "proportion": 0.02,
    "total_votes_location": 6235
  },
  {
    "location_id": 1223,
    "votes": 2,
    "proportion": 0.04,
    "total_votes_location": 4465
  },
  {
    "location_id": 1063,
    "votes": 1,
    "proportion": 0.02,
    "total_votes_location": 5429
  },
  {
    "location_id": 479,
    "votes": 1,
    "proportion": 0.03,
    "total_votes_location": 3196
  },
  {
    "location_id": 1096,
    "votes": 1,
    "proportion": 0.01,
    "total_votes_location": 8684
  },
  {
    "location_id": 575,
    "votes": 1,
    "proportion": 0.01,
    "total_votes_location": 8478
  },
  {
    "location_id": 85,
    "votes": 1,
    "proportion": 0.03,
    "total_votes_location": 3953
  },
  {
    "location_id": 1155,
    "votes": 4,
    "proportion": 0.07,
    "total_votes_location": 5859
  },
  {
    "location_id": 121,
    "votes": 2,
    "proportion": 0.09,
    "total_votes_location": 2210
  },
  {
    "location_id": 680,
    "votes": 2,
    "proportion": 0.03,
    "total_votes_location": 6609
  },
  {
    "location_id": 259,
    "votes": 1,
    "proportion": 0.04,
    "total_votes_location": 2542
  },
  {
    "location_id": 235,
    "votes": 1,
    "proportion": 0.01,
    "total_votes_location": 7527
  },
  {
    "location_id": 799,
    "votes": 1,
    "proportion": 0.01,
    "total_votes_location": 6987
  },
  {
    "location_id": 818,
    "votes": 1,
    "proportion": 0.03,
    "total_votes_location": 3323
  },
  {
    "location_id": 857,
    "votes": 1,
    "proportion": 0.07,
    "total_votes_location": 1536
  },
  {
    "location_id": 661,
    "votes": 1,
    "proportion": 0.04,
    "total_votes_location": 2297
  },
  {
    "location_id": 983,
    "votes": 1,
    "proportion": 0.02,
    "total_votes_location": 4482
  },
  {
    "location_id": 951,
    "votes": 1,
    "proportion": 0.03,
    "total_votes_location": 3269
  },
  {
    "location_id": 1345,
    "votes": 1,
    "proportion": 0.03,
    "total_votes_location": 3242
  },
  {
    "location_id": 434,
    "votes": 1,
    "proportion": 0.02,
    "total_votes_location": 5658
  },
  {
    "location_id": 1263,
    "votes": 2,
    "proportion": 0.02,
    "total_votes_location": 9330
  },
  {
    "location_id": 1098,
    "votes": 1,
    "proportion": 0.03,
    "total_votes_location": 3877
  },
  {
    "location_id": 1099,
    "votes": 1,
    "proportion": 0.02,
    "total_votes_location": 4300
  },
  {
    "location_id": 1352,
    "votes": 1,
    "proportion": 0.02,
    "total_votes_location": 4796
  },
  {
    "location_id": 298,
    "votes": 1,
    "proportion": 0.02,
    "total_votes_location": 5756
  },
  {
    "location_id": 824,
    "votes": 3,
    "proportion": 0.03,
    "total_votes_location": 10685
  },
  {
    "location_id": 723,
    "votes": 1,
    "proportion": 0.01,
    "total_votes_location": 6888
  },
  {
    "location_id": 431,
    "votes": 3,
    "proportion": 0.04,
    "total_votes_location": 7238
  },
  {
    "location_id": 935,
    "votes": 1,
    "proportion": 0.03,
    "total_votes_location": 3907
  },
  {
    "location_id": 1103,
    "votes": 1,
    "proportion": 0.01,
    "total_votes_location": 7325
  },
  {
    "location_id": 98,
    "votes": 1,
    "proportion": 0.02,
    "total_votes_location": 4100
  }
]