[
  {
    "location_id": 453,
    "votes": 1,
    "proportion": 0.02,
    "total_votes_location": 6079
  },
  {
    "location_id": 682,
    "votes": 2,
    "proportion": 0.05,
    "total_votes_location": 4185
  },
  {
    "location_id": 581,
    "votes": 2,
    "proportion": 0.08,
    "total_votes_location": 2523
  },
  {
    "location_id": 219,
    "votes": 1,
    "proportion": 0.02,
    "total_votes_location": 4264
  },
  {
    "location_id": 808,
    "votes": 16,
    "proportion": 0.34,
    "total_votes_location": 4656
  },
  {
    "location_id": 154,
    "votes": 1,
    "proportion": 0.02,
    "total_votes_location": 4427
  },
  {
    "location_id": 305,
    "votes": 3,
    "proportion": 0.19,
    "total_votes_location": 1615
  },
  {
    "location_id": 1334,
    "votes": 1,
    "proportion": 0.03,
    "total_votes_location": 3834
  },
  {
    "location_id": 188,
    "votes": 2,
    "proportion": 0.06,
    "total_votes_location": 3247
  },
  {
    "location_id": 1193,
    "votes": 7,
    "proportion": 0.09,
    "total_votes_location": 7674
  },
  {
    "location_id": 478,
    "votes": 76,
    "proportion": 1.91,
    "total_votes_location": 3969
  },
  {
    "location_id": 775,
    "votes": 1,
    "proportion": 0.02,
    "total_votes_location": 5245
  },
  {
    "location_id": 598,
    "votes": 3,
    "proportion": 0.07,
    "total_votes_location": 4086
  },
  {
    "location_id": 153,
    "votes": 1,
    "proportion": 0.03,
    "total_votes_location": 3676
  },
  {
    "location_id": 726,
    "votes": 1,
    "proportion": 0.02,
    "total_votes_location": 5515
  },
  {
    "location_id": 1158,
    "votes": 1,
    "proportion": 0.02,
    "total_votes_location": 6306
  },
  {
    "location_id": 1294,
    "votes": 5,
    "proportion": 0.26,
    "total_votes_location": 1896
  },
  {
    "location_id": 246,
    "votes": 1,
    "proportion": 0.02,
    "total_votes_location": 6162
  },
  {
    "location_id": 651,
    "votes": 1,
    "proportion": 0.04,
    "total_votes_location": 2583
  },
  {
    "location_id": 434,
    "votes": 1,
    "proportion": 0.02,
    "total_votes_location": 5658
  },
  {
    "location_id": 546,
    "votes": 1,
    "proportion": 0.01,
    "total_votes_location": 9387
  },
  {
    "location_id": 605,
    "votes": 1,
    "proportion": 0.01,
    "total_votes_location": 7688
  },
  {
    "location_id": 1284,
    "votes": 31,
    "proportion": 0.74,
    "total_votes_location": 4181
  },
  {
    "location_id": 304,
    "votes": 37,
    "proportion": 0.95,
    "total_votes_location": 3889
  },
  {
    "location_id": 815,
    "votes": 3,
    "proportion": 0.04,
    "total_votes_location": 7092
  },
  {
    "location_id": 118,
    "votes": 1,
    "proportion": 0.03,
    "total_votes_location": 3468
  },
  {
    "location_id": 652,
    "votes": 19,
    "proportion": 0.47,
    "total_votes_location": 4066
  },
  {
    "location_id": 471,
    "votes": 1,
    "proportion": 0.03,
    "total_votes_location": 3127
  },
  {
    "location_id": 907,
    "votes": 1,
    "proportion": 0.02,
    "total_votes_location": 4186
  },
  {
    "location_id": 1213,
    "votes": 10,
    "proportion": 0.14,
    "total_votes_location": 7124
  },
  {
    "location_id": 1279,
    "votes": 7,
    "proportion": 0.2,
    "total_votes_location": 3435
  },
  {
    "location_id": 1345,
    "votes": 1,
    "proportion": 0.03,
    "total_votes_location": 3242
  },
  {
    "location_id": 1024,
    "votes": 4,
    "proportion": 0.08,
    "total_votes_location": 4910
  },
  {
    "location_id": 495,
    "votes": 24,
    "proportion": 0.36,
    "total_votes_location": 6686
  },
  {
    "location_id": 1325,
    "votes": 2,
    "proportion": 0.15,
    "total_votes_location": 1294
  },
  {
    "location_id": 459,
    "votes": 8,
    "proportion": 1.62,
    "total_votes_location": 495
  },
  {
    "location_id": 214,
    "votes": 1,
    "proportion": 0.01,
    "total_votes_location": 7634
  },
  {
    "location_id": 1212,
    "votes": 1,
    "proportion": 0.03,
    "total_votes_location": 3928
  },
  {
    "location_id": 106,
    "votes": 2,
    "proportion": 0.04,
    "total_votes_location": 5078
  },
  {
    "location_id": 991,
    "votes": 1,
    "proportion": 0.03,
    "total_votes_location": 3648
  },
  {
    "location_id": 303,
    "votes": 11,
    "proportion": 0.33,
    "total_votes_location": 3313
  },
  {
    "location_id": 1095,
    "votes": 21,
    "proportion": 0.29,
    "total_votes_location": 7142
  },
  {
    "location_id": 855,
    "votes": 2,
    "proportion": 0.08,
    "total_votes_location": 2406
  },
  {
    "location_id": 955,
    "votes": 1,
    "proportion": 0.02,
    "total_votes_location": 4138
  },
  {
    "location_id": 496,
    "votes": 3,
    "proportion": 0.04,
    "total_votes_location": 7670
  },
  {
    "location_id": 971,
    "votes": 1,
    "proportion": 0.02,
    "total_votes_location": 5674
  },
  {
    "location_id": 446,
    "votes": 1,
    "proportion": 0.02,
    "total_votes_location": 6303
  }
]